xrpl_toolkit/__init__.py
xrpl_toolkit/xrp_toolkit.py
XRP_BASE-0.1.4.dist-info/METADATA
XRP_BASE-0.1.4.dist-info/WHEEL
XRP_BASE-0.1.4.dist-info/entry_points.txt
XRP_BASE-0.1.4.dist-info/top_level.txt
XRP_BASE-0.1.4.dist-info/RECORD
