Metadata-Version: 2.2
Name: XRP-BASE
Version: 0.1.4
Summary: A Python package for XRPL transactions and installations.
Author: Your Name
Requires-Python: >=3.6
Requires-Dist: requests
Requires-Dist: base58
Requires-Dist: pandas
Requires-Dist: numpy
Requires-Dist: tqdm
Requires-Dist: matplotlib
Requires-Dist: scikit-learn
Requires-Dist: flask
Requires-Dist: beautifulsoup4
Requires-Dist: pytest
Requires-Dist: pydantic
Requires-Dist: asyncio
Dynamic: author
Dynamic: description
Dynamic: description-content-type
Dynamic: requires-dist
Dynamic: requires-python
Dynamic: summary
